CJiaochengCYuyanBianchengWangFix1/README.md
CJiaochengCYuyanBianchengWangFix1/__init__.py
CJiaochengCYuyanBianchengWangFix1/__main__.py
CJiaochengCYuyanBianchengWangFix1/file.epub
CJiaochengCYuyanBianchengWangFix1/index.html
CJiaochengCYuyanBianchengWangFix1/css/__init__.py
CJiaochengCYuyanBianchengWangFix1/css/annotations.css
CJiaochengCYuyanBianchengWangFix1/css/main.css
CJiaochengCYuyanBianchengWangFix1/css/normalize.css
CJiaochengCYuyanBianchengWangFix1/css/popup.css
CJiaochengCYuyanBianchengWangFix1/font/__init__.py
CJiaochengCYuyanBianchengWangFix1/font/fontello.eot
CJiaochengCYuyanBianchengWangFix1/font/fontello.svg
CJiaochengCYuyanBianchengWangFix1/font/fontello.ttf
CJiaochengCYuyanBianchengWangFix1/font/fontello.woff
CJiaochengCYuyanBianchengWangFix1/img/__init__.py
CJiaochengCYuyanBianchengWangFix1/img/annotator-glyph-sprite.png
CJiaochengCYuyanBianchengWangFix1/img/annotator-icon-sprite.png
CJiaochengCYuyanBianchengWangFix1/img/apple-touch-icon.png
CJiaochengCYuyanBianchengWangFix1/img/cancelfullscreen.png
CJiaochengCYuyanBianchengWangFix1/img/close.png
CJiaochengCYuyanBianchengWangFix1/img/fullscreen.png
CJiaochengCYuyanBianchengWangFix1/img/loader.gif
CJiaochengCYuyanBianchengWangFix1/img/menu-icon.png
CJiaochengCYuyanBianchengWangFix1/img/save.png
CJiaochengCYuyanBianchengWangFix1/img/saved.png
CJiaochengCYuyanBianchengWangFix1/img/settings-s.png
CJiaochengCYuyanBianchengWangFix1/img/settings.png
CJiaochengCYuyanBianchengWangFix1/img/star.png
CJiaochengCYuyanBianchengWangFix1/js/__init__.py
CJiaochengCYuyanBianchengWangFix1/js/epub.js
CJiaochengCYuyanBianchengWangFix1/js/epub.min.js
CJiaochengCYuyanBianchengWangFix1/js/epub.min.map
CJiaochengCYuyanBianchengWangFix1/js/hooks.min.js
CJiaochengCYuyanBianchengWangFix1/js/hooks.min.map
CJiaochengCYuyanBianchengWangFix1/js/reader.js
CJiaochengCYuyanBianchengWangFix1/js/reader.js.map
CJiaochengCYuyanBianchengWangFix1/js/reader.min.js
CJiaochengCYuyanBianchengWangFix1/js/reader.min.map
c_jiaocheng_c_yuyan_biancheng_wang_fix1-2025.3.24.0.dist-info/METADATA
c_jiaocheng_c_yuyan_biancheng_wang_fix1-2025.3.24.0.dist-info/WHEEL
c_jiaocheng_c_yuyan_biancheng_wang_fix1-2025.3.24.0.dist-info/entry_points.txt
c_jiaocheng_c_yuyan_biancheng_wang_fix1-2025.3.24.0.dist-info/top_level.txt
c_jiaocheng_c_yuyan_biancheng_wang_fix1-2025.3.24.0.dist-info/RECORD
